ism.py
ism-1.0.3.dist-info/LICENSE
ism-1.0.3.dist-info/METADATA
ism-1.0.3.dist-info/WHEEL
ism-1.0.3.dist-info/entry_points.txt
ism-1.0.3.dist-info/top_level.txt
ism-1.0.3.dist-info/RECORD
