Metadata-Version: 2.1
Name: ism
Version: 1.0.3
Summary: Interactive SSH menu
Home-page: https://github.com/Sch-Tomi/ism
Author: Sch-Tomi
License: UNKNOWN
Platform: UNKNOWN
Classifier: Development Status :: 5 - Production/Stable
Classifier: Programming Language :: Python :: 3
Classifier: License :: OSI Approved :: GNU General Public License v3 (GPLv3)
Classifier: Operating System :: OS Independent
Requires-Python: >=3.6
Requires-Dist: questionary
